MANIFEST.in
setup.py
gentle_django_mongo/METADATA
gentle_django_mongo/__init__.py
gentle_django_mongo/fields.py
gentle_django_mongo/filter.py
gentle_django_mongo/manager.py
gentle_django_mongo/model.py
gentle_django_mongo/queryset.py
gentle_django_mongo/utils.py
gentle_django_mongo.egg-info/PKG-INFO
gentle_django_mongo.egg-info/SOURCES.txt
gentle_django_mongo.egg-info/dependency_links.txt
gentle_django_mongo.egg-info/requires.txt
gentle_django_mongo.egg-info/top_level.txt