Metadata-Version: 1.1
Name: gentle-django-mongo
Version: 0.0.1
Summary: Django Model interface for mongo models
Home-page: UNKNOWN
Author: Sebastian Phelps
Author-email: sebastian.phelps@gmail.com
License: UNKNOWN
Keywords: gentle_django_mongo mongo django model
Platform: UNKNOWN
Requires: django (>=1.4.1)
Requires: pymongo (>=2.7.1)
